{"fields":{"F1":{"title":"醫務本業利益/虧損","rankTitle":"醫務本業利益/虧損排名","unit":"億元"},"F2":{"title":"非醫務本業利益/虧損","rankTitle":"非醫務本業利益/虧損排名","unit":"億元"},"F3":{"title":"整體獲利/虧損","rankTitle":"整體獲利/虧損排名","unit":"億元"},"F5":{"title":"醫務利益率","rankTitle":"醫務利益率排名","unit":"百分比"},"F6":{"title":"醫務收入","rankTitle":"醫務收入排名","unit":"億元"},"F7":{"title":"醫務成本","rankTitle":"醫務成本排名","unit":"億元"},"F8":{"title":"全日平均護病比","rankTitle":"全日平均護病比排名","unit":"人"},"DOCTOR":{"title":"醫師數","rankTitle":"醫師數排名","unit":"人數"},"BED":{"title":"病床數","rankTitle":"病床數排名","unit":"床"},"PT_ALL":{"title":"門住合計醫療點數","rankTitle":"門住合計醫療點數排名","unit":"億點"},"OPD_CNT":{"title":"門診件數","rankTitle":"門診件數排名","unit":"萬件"},"OPD_PT":{"title":"門診醫療點數","rankTitle":"門診醫療點數排名","unit":"億點"},"IPD_CNT":{"title":"住診件數","rankTitle":"住診件數排名","unit":"萬件"},"IPD_PT":{"title":"住診醫療點數","rankTitle":"住診醫療點數排名","unit":"億點"},"IPD_DAY":{"title":"住院天數","rankTitle":"住院天數排名","unit":"萬日"}},"code":"0102070020","name":"大同醫院","shortName":"大同醫院","rows":[{"YEAR":"104","HOSP_CNT_TYPNAM":"區域醫院","REGION":"高屏","F1Val":"3.22","F1Rank":11,"F2Val":"-0.41","F3Val":"2.81","F3Rank":20,"F5Val":"12.75%","F5Rank":2,"F6Val":"25.27","F6Rank":53,"F7Val":"22.05","F8Val":"9.9","DOCTORVal":"88","DOCTORRank":71,"BEDVal":"388","BEDRank":93,"PT_ALLVal":"22.10","OPD_CNTVal":"60.84","OPD_CNTRank":48,"OPD_PTVal":"14.49","IPD_CNTVal":"1.52","IPD_PTVal":"7.60","IPD_DAYVal":"9.77","IPD_DAYRank":83},{"YEAR":"105","HOSP_CNT_TYPNAM":"區域醫院","REGION":"高屏","F1Val":"3.89","F1Rank":8,"F2Val":"-0.58","F3Val":"3.31","F3Rank":20,"F5Val":"13.56%","F5Rank":2,"F6Val":"28.68","F6Rank":49,"F7Val":"24.79","F8Val":"8.7","DOCTORVal":"92","DOCTORRank":70,"BEDVal":"389","BEDRank":98,"PT_ALLVal":"23.98","OPD_CNTVal":"66.47","OPD_CNTRank":48,"OPD_PTVal":"15.82","IPD_CNTVal":"1.51","IPD_PTVal":"8.16","IPD_DAYVal":"9.96","IPD_DAYRank":87},{"YEAR":"106","HOSP_CNT_TYPNAM":"區域醫院","REGION":"高屏","F1Val":"4.25","F1Rank":7,"F2Val":"-0.52","F3Val":"3.72","F3Rank":20,"F5Val":"13.02%","F5Rank":2,"F6Val":"32.61","F6Rank":45,"F7Val":"25.75","F8Val":"9.8","DOCTORVal":"101","DOCTORRank":66,"BEDVal":"411","BEDRank":94,"PT_ALLVal":"27.82","OPD_CNTVal":"72.96","OPD_CNTRank":44,"OPD_PTVal":"18.23","IPD_CNTVal":"1.67","IPD_PTVal":"9.60","IPD_DAYVal":"10.82","IPD_DAYRank":81},{"YEAR":"107","HOSP_CNT_TYPNAM":"區域醫院","REGION":"高屏","F1Val":"4.28","F1Rank":7,"F2Val":"-0.51","F3Val":"3.77","F3Rank":17,"F5Val":"12.92%","F5Rank":7,"F6Val":"33.13","F6Rank":47,"F7Val":"26.23","F8Val":"9.6","DOCTORVal":"99","DOCTORRank":68,"BEDVal":"411","BEDRank":104,"PT_ALLVal":"29.80","OPD_CNTVal":"76.57","OPD_CNTRank":43,"OPD_PTVal":"19.80","IPD_CNTVal":"1.72","IPD_PTVal":"10.00","IPD_DAYVal":"11.08","IPD_DAYRank":88},{"YEAR":"108","HOSP_CNT_TYPNAM":"區域醫院","REGION":"高屏","F1Val":"5.96","F1Rank":4,"F2Val":"-0.56","F3Val":"5.40","F3Rank":15,"F5Val":"15.99%","F5Rank":3,"F6Val":"37.29","F6Rank":45,"F7Val":"28.53","F8Val":"10.6","DOCTORVal":"107","DOCTORRank":66,"BEDVal":"421","BEDRank":99,"PT_ALLVal":"31.91","OPD_CNTVal":"75.87","OPD_CNTRank":43,"OPD_PTVal":"21.23","IPD_CNTVal":"1.81","IPD_PTVal":"10.69","IPD_DAYVal":"11.64","IPD_DAYRank":85},{"YEAR":"109","HOSP_CNT_TYPNAM":"區域醫院","REGION":"高屏區","F1Val":"5.90","F1Rank":5,"F2Val":"-0.49","F3Val":"5.41","F3Rank":20,"F5Val":"15.70%","F5Rank":4,"F6Val":"37.57","F6Rank":46,"F7Val":"28.81","F8Val":"9.9","DOCTORVal":"115","DOCTORRank":60,"BEDVal":"430","BEDRank":97,"PT_ALLVal":"31.56","OPD_CNTVal":"78.66","OPD_CNTRank":40,"OPD_PTVal":"21.10","IPD_CNTVal":"1.71","IPD_PTVal":"10.46","IPD_DAYVal":"10.39","IPD_DAYRank":93},{"YEAR":"110","HOSP_CNT_TYPNAM":"區域醫院","REGION":"高屏","F1Val":"6.15","F1Rank":6,"F2Val":"-0.72","F3Val":"5.43","F3Rank":21,"F5Val":"16.01%","F5Rank":3,"F6Val":"38.40","F6Rank":47,"F7Val":"29.33","F8Val":"8.9","DOCTORVal":"128","DOCTORRank":59,"BEDVal":"436","BEDRank":98,"PT_ALLVal":"32.14","OPD_CNTVal":"78.13","OPD_CNTRank":38,"OPD_PTVal":"21.78","IPD_CNTVal":"1.51","IPD_PTVal":"10.37","IPD_DAYVal":"9.94","IPD_DAYRank":94},{"YEAR":"111","HOSP_CNT_TYPNAM":"區域醫院","REGION":"高屏","F1Val":"5.81","F1Rank":11,"F2Val":"0.36","F3Val":"6.17","F3Rank":22,"F5Val":"13.87%","F5Rank":9,"F6Val":"41.91","F6Rank":48,"F7Val":"32.92","F8Val":"9.8","DOCTORVal":"125","DOCTORRank":61,"BEDVal":"407","BEDRank":93,"PT_ALLVal":"32.73","OPD_CNTVal":"82.07","OPD_CNTRank":41,"OPD_PTVal":"22.17","IPD_CNTVal":"1.58","IPD_PTVal":"10.57","IPD_DAYVal":"11.51","IPD_DAYRank":81},{"YEAR":"112","HOSP_CNT_TYPNAM":"區域醫院","REGION":"高屏","F1Val":"5.24","F1Rank":12,"F2Val":"-0.04","F3Val":"5.20","F3Rank":27,"F5Val":"12.45%","F5Rank":11,"F6Val":"42.08","F6Rank":52,"F7Val":"33.53","F8Val":"9.2","DOCTORVal":"126","DOCTORRank":63,"BEDVal":"510","BEDRank":82,"PT_ALLVal":"34.40","OPD_CNTVal":"85.17","OPD_CNTRank":41,"OPD_PTVal":"22.80","IPD_CNTVal":"1.74","IPD_PTVal":"11.59","IPD_DAYVal":"11.64","IPD_DAYRank":82},{"YEAR":"113","HOSP_CNT_TYPNAM":"區域醫院","REGION":"高屏","F1Val":"-1.49","F1Rank":230,"F2Val":"0.68","F3Val":"-0.81","F3Rank":237,"F5Val":"-3.63%","F5Rank":221,"F6Val":"41.13","F6Rank":55,"F7Val":"35.67","F8Val":"8.3","DOCTORVal":"112","DOCTORRank":68,"BEDVal":"503","BEDRank":85,"PT_ALLVal":"32.28","OPD_CNTVal":"80.47","OPD_CNTRank":49,"OPD_PTVal":"21.32","IPD_CNTVal":"1.60","IPD_PTVal":"10.96","IPD_DAYVal":"10.97","IPD_DAYRank":88}]}