{"fields":{"F1":{"title":"醫務本業利益/虧損","rankTitle":"醫務本業利益/虧損排名","unit":"億元"},"F2":{"title":"非醫務本業利益/虧損","rankTitle":"非醫務本業利益/虧損排名","unit":"億元"},"F3":{"title":"整體獲利/虧損","rankTitle":"整體獲利/虧損排名","unit":"億元"},"F5":{"title":"醫務利益率","rankTitle":"醫務利益率排名","unit":"百分比"},"F6":{"title":"醫務收入","rankTitle":"醫務收入排名","unit":"億元"},"F7":{"title":"醫務成本","rankTitle":"醫務成本排名","unit":"億元"},"F8":{"title":"全日平均護病比","rankTitle":"全日平均護病比排名","unit":"人"},"DOCTOR":{"title":"醫師數","rankTitle":"醫師數排名","unit":"人數"},"BED":{"title":"病床數","rankTitle":"病床數排名","unit":"床"},"PT_ALL":{"title":"門住合計醫療點數","rankTitle":"門住合計醫療點數排名","unit":"億點"},"OPD_CNT":{"title":"門診件數","rankTitle":"門診件數排名","unit":"萬件"},"OPD_PT":{"title":"門診醫療點數","rankTitle":"門診醫療點數排名","unit":"億點"},"IPD_CNT":{"title":"住診件數","rankTitle":"住診件數排名","unit":"萬件"},"IPD_PT":{"title":"住診醫療點數","rankTitle":"住診醫療點數排名","unit":"億點"},"IPD_DAY":{"title":"住院天數","rankTitle":"住院天數排名","unit":"萬日"}},"code":"1317040039","name":"中山中興","shortName":"中山中興","rows":[{"YEAR":"107","HOSP_CNT_TYPNAM":"地區醫院","REGION":"中區","F1Val":"0.45","F1Rank":63,"F2Val":"0.00","F3Val":"0.45","F3Rank":90,"F5Val":"10.90%","F5Rank":11,"F6Val":"4.10","F6Rank":179,"F7Val":"3.36","F8Val":"8.1","DOCTORVal":"16","DOCTORRank":188,"BEDVal":"142","BEDRank":172,"PT_ALLVal":"4.23","OPD_CNTVal":"9.21","OPD_CNTRank":187,"OPD_PTVal":"3.35","IPD_CNTVal":"0.09","IPD_PTVal":"0.88","IPD_DAYVal":"2.43","IPD_DAYRank":176},{"YEAR":"108","HOSP_CNT_TYPNAM":"地區醫院","REGION":"中區","F1Val":"0.56","F1Rank":69,"F2Val":"-0.01","F3Val":"0.56","F3Rank":82,"F5Val":"12.45%","F5Rank":7,"F6Val":"4.53","F6Rank":180,"F7Val":"3.68","F8Val":"9.2","DOCTORVal":"16","DOCTORRank":189,"BEDVal":"142","BEDRank":172,"PT_ALLVal":"4.69","OPD_CNTVal":"11.43","OPD_CNTRank":180,"OPD_PTVal":"3.76","IPD_CNTVal":"0.08","IPD_PTVal":"0.93","IPD_DAYVal":"2.57","IPD_DAYRank":177},{"YEAR":"109","HOSP_CNT_TYPNAM":"地區醫院","REGION":"中區","F1Val":"0.54","F1Rank":68,"F2Val":"-0.01","F3Val":"0.53","F3Rank":93,"F5Val":"11.09%","F5Rank":9,"F6Val":"4.88","F6Rank":181,"F7Val":"4.03","F8Val":"8.4","DOCTORVal":"16","DOCTORRank":195,"BEDVal":"141","BEDRank":181,"PT_ALLVal":"4.86","OPD_CNTVal":"12.73","OPD_CNTRank":172,"OPD_PTVal":"4.04","IPD_CNTVal":"0.07","IPD_PTVal":"0.81","IPD_DAYVal":"2.19","IPD_DAYRank":186},{"YEAR":"110","HOSP_CNT_TYPNAM":"地區醫院","REGION":"中區","F1Val":"0.31","F1Rank":105,"F2Val":"-0.00","F3Val":"0.31","F3Rank":129,"F5Val":"6.50%","F5Rank":35,"F6Val":"4.80","F6Rank":181,"F7Val":"4.16","F8Val":"8.2","DOCTORVal":"17","DOCTORRank":188,"BEDVal":"141","BEDRank":181,"PT_ALLVal":"4.93","OPD_CNTVal":"12.89","OPD_CNTRank":169,"OPD_PTVal":"4.12","IPD_CNTVal":"0.07","IPD_PTVal":"0.81","IPD_DAYVal":"2.16","IPD_DAYRank":185},{"YEAR":"111","HOSP_CNT_TYPNAM":"地區醫院","REGION":"中區","F1Val":"0.50","F1Rank":107,"F2Val":"-0.01","F3Val":"0.49","F3Rank":137,"F5Val":"9.52%","F5Rank":31,"F6Val":"5.26","F6Rank":182,"F7Val":"4.44","F8Val":"8.7","DOCTORVal":"17","DOCTORRank":191,"BEDVal":"99","BEDRank":192,"PT_ALLVal":"5.08","OPD_CNTVal":"14.01","OPD_CNTRank":167,"OPD_PTVal":"4.33","IPD_CNTVal":"0.08","IPD_PTVal":"0.75","IPD_DAYVal":"1.98","IPD_DAYRank":191},{"YEAR":"112","HOSP_CNT_TYPNAM":"地區醫院","REGION":"中區","F1Val":"0.67","F1Rank":89,"F2Val":"-0.00","F3Val":"0.67","F3Rank":112,"F5Val":"12.40%","F5Rank":12,"F6Val":"5.40","F6Rank":183,"F7Val":"4.42","F8Val":"8.8","DOCTORVal":"16","DOCTORRank":201,"BEDVal":"141","BEDRank":183,"PT_ALLVal":"5.26","OPD_CNTVal":"15.18","OPD_CNTRank":169,"OPD_PTVal":"4.49","IPD_CNTVal":"0.08","IPD_PTVal":"0.77","IPD_DAYVal":"2.00","IPD_DAYRank":191},{"YEAR":"113","HOSP_CNT_TYPNAM":"地區醫院","REGION":"中區","F1Val":"0.89","F1Rank":64,"F2Val":"0.02","F3Val":"0.90","F3Rank":91,"F5Val":"15.69%","F5Rank":5,"F6Val":"5.66","F6Rank":186,"F7Val":"4.45","F8Val":"8.5","DOCTORVal":"15","DOCTORRank":214,"BEDVal":"128","BEDRank":193,"PT_ALLVal":"5.30","OPD_CNTVal":"15.69","OPD_CNTRank":168,"OPD_PTVal":"4.55","IPD_CNTVal":"0.07","IPD_PTVal":"0.75","IPD_DAYVal":"1.94","IPD_DAYRank":195}]}