{"fields":{"F1":{"title":"醫務本業利益/虧損","rankTitle":"醫務本業利益/虧損排名","unit":"億元"},"F2":{"title":"非醫務本業利益/虧損","rankTitle":"非醫務本業利益/虧損排名","unit":"億元"},"F3":{"title":"整體獲利/虧損","rankTitle":"整體獲利/虧損排名","unit":"億元"},"F5":{"title":"醫務利益率","rankTitle":"醫務利益率排名","unit":"百分比"},"F6":{"title":"醫務收入","rankTitle":"醫務收入排名","unit":"億元"},"F7":{"title":"醫務成本","rankTitle":"醫務成本排名","unit":"億元"},"F8":{"title":"全日平均護病比","rankTitle":"全日平均護病比排名","unit":"人"}},"code":"1317040011","name":"中山醫學大學附設醫院","shortName":"中山附醫","rows":[{"YEAR":"104","HOSP_CNT_TYPNAM":"醫學中心","F1Val":"3.37","F1Rank":9,"F2Val":"0.87","F2Rank":32,"F3Val":"4.24","F3Rank":12,"F5Val":"5.66%","F6Val":"59.45","F7Val":"54.82","F8Val":"7.8"},{"YEAR":"105","HOSP_CNT_TYPNAM":"醫學中心","F1Val":"1.05","F1Rank":34,"F2Val":"0.83","F2Rank":37,"F3Val":"1.87","F3Rank":32,"F5Val":"1.74%","F6Val":"60.22","F7Val":"57.83","F8Val":"7.9"},{"YEAR":"106","HOSP_CNT_TYPNAM":"醫學中心","F1Val":"2.93","F1Rank":15,"F2Val":"0.65","F2Rank":35,"F3Val":"3.58","F3Rank":22,"F5Val":"4.34%","F6Val":"67.52","F7Val":"63.28","F8Val":"7.9"},{"YEAR":"107","HOSP_CNT_TYPNAM":"醫學中心","F1Val":"1.93","F1Rank":19,"F2Val":"0.95","F2Rank":38,"F3Val":"2.87","F3Rank":25,"F5Val":"2.97%","F6Val":"64.75","F7Val":"61.71","F8Val":"7.7"},{"YEAR":"108","HOSP_CNT_TYPNAM":"醫學中心","F1Val":"0.61","F1Rank":65,"F2Val":"1.36","F2Rank":32,"F3Val":"1.97","F3Rank":37,"F5Val":"0.86%","F6Val":"70.82","F7Val":"69.10","F8Val":"7.8"},{"YEAR":"109","HOSP_CNT_TYPNAM":"醫學中心","F1Val":"4.92","F1Rank":9,"F2Val":"1.72","F2Rank":26,"F3Val":"6.64","F3Rank":12,"F5Val":"5.98%","F6Val":"82.38","F7Val":"76.43","F8Val":"7.4"},{"YEAR":"110","HOSP_CNT_TYPNAM":"醫學中心","F1Val":"5.07","F1Rank":11,"F2Val":"1.66","F2Rank":34,"F3Val":"6.73","F3Rank":15,"F5Val":"5.63%","F6Val":"90.14","F7Val":"83.97","F8Val":"7.4"},{"YEAR":"111","HOSP_CNT_TYPNAM":"醫學中心","F1Val":"5.06","F1Rank":16,"F2Val":"3.19","F2Rank":21,"F3Val":"8.25","F3Rank":15,"F5Val":"4.99%","F6Val":"101.42","F7Val":"95.24","F8Val":"7.4"},{"YEAR":"112","HOSP_CNT_TYPNAM":"醫學中心","F1Val":"8.20","F1Rank":4,"F2Val":"3.91","F2Rank":16,"F3Val":"12.11","F3Rank":11,"F5Val":"7.53%","F6Val":"108.90","F7Val":"99.38","F8Val":"7.5"}]}